{
  "generated_at_utc": "2026-04-18T18:14:25.766731+00:00",
  "hours_window": 2,
  "items": [
    {
      "channel": "лав соса",
      "title": "Выживание В Тайланде На 1 ДОЛЛАР ( это было очень тяжело )",
      "url": "https://youtu.be/N1jJmUmMol0",
      "published_at_utc": "2026-04-18T18:13:24.193686+00:00",
      "age_seconds": 0
    },
    {
      "channel": "лав соса",
      "title": "Шах Подвозит Дилблина И Даню Лейзи ( моя подработка )",
      "url": "https://youtu.be/1sspKtB3j5A",
      "published_at_utc": "2026-04-18T18:13:24.193686+00:00",
      "age_seconds": 0
    },
    {
      "channel": "Объяпонился",
      "title": "10 гениальных вещей из Японии и Кореи, которые вас удивят 😯",
      "url": "https://youtu.be/O2QuCTeARUY",
      "published_at_utc": "2026-04-18T18:12:54.769693+00:00",
      "age_seconds": 0
    },
    {
      "channel": "Марк Аддерли",
      "title": "ТВИКИ КОТОРЫЕ СДЕЛАЮТ ТЕБЕ ИДЕАЛЬНУЮ WINDOWS 11!",
      "url": "https://youtu.be/u_KLunRD8-s",
      "published_at_utc": "2026-04-18T18:12:43.881141+00:00",
      "age_seconds": 0
    },
    {
      "channel": "Марк Аддерли",
      "title": "ЕЩЁ ОДИН ШКОЛЬНЫЙ НОУТБУК ИЗ АМЕРИКИ",
      "url": "https://youtu.be/JDGPV4qCXMw",
      "published_at_utc": "2026-04-18T18:12:43.881141+00:00",
      "age_seconds": 0
    },
    {
      "channel": "Шайнов",
      "title": "Я ИСПЫТАЛ ХУДШИЕ ТЮРЕМНЫЕ ПЫТКИ (см*ртельно!)",
      "url": "https://youtu.be/TB2o6Oteiqs",
      "published_at_utc": "2026-04-18T18:12:29.965709+00:00",
      "age_seconds": 0
    },
    {
      "channel": "Шайнов",
      "title": "Я ИСПЫТАЛ ХУДШИЕ ПЫТКИ СРЕДНЕВЕКОВЬЯ (30 дней ада)",
      "url": "https://youtu.be/LpfevPkWqj4",
      "published_at_utc": "2026-04-18T18:12:29.965709+00:00",
      "age_seconds": 0
    },
    {
      "channel": "dikiy_vadik",
      "title": "Та самая добрая соседка",
      "url": "https://www.youtube.com/shorts/8cZSKAy0qWo",
      "published_at_utc": "2026-04-18T18:06:33+00:00",
      "age_seconds": 384
    },
    {
      "channel": "Завод KURS",
      "title": "ТОП-3 УБИЙСТВЕННЫХ СНАЙПЕРСКИХ ВИНТОВОК🔥",
      "url": "https://www.youtube.com/shorts/t21l7Hr45wk",
      "published_at_utc": "2026-04-18T18:04:17+00:00",
      "age_seconds": 515
    },
    {
      "channel": "kinoluv",
      "title": "Добрый король даровал джинну свободу🧞‍♂️",
      "url": "https://www.youtube.com/shorts/Kv7FVS0PnEE",
      "published_at_utc": "2026-04-18T18:04:01+00:00",
      "age_seconds": 511
    },
    {
      "channel": "МайорКрафт",
      "title": "Когда у хомяка большие глаза #фильм #сериал #моменты",
      "url": "https://www.youtube.com/shorts/s5zaQPGqwJc",
      "published_at_utc": "2026-04-18T17:46:40+00:00",
      "age_seconds": 1579
    },
    {
      "channel": "Тру Шорты",
      "title": "В пустыне было одно дерево...и это случилось",
      "url": "https://www.youtube.com/shorts/oTLvIwyhAwg",
      "published_at_utc": "2026-04-18T17:35:21+00:00",
      "age_seconds": 2198
    },
    {
      "channel": "i11ushenka",
      "title": "Продолжение споров из-за ЗП (ft. Испания)",
      "url": "https://www.youtube.com/shorts/Kk78y_yoaPk",
      "published_at_utc": "2026-04-18T17:26:23+00:00",
      "age_seconds": 2744
    },
    {
      "channel": "Team Spirit CS",
      "title": "TEAM SPIRIT: IEM RIO 2026. VLOG 2",
      "url": "https://www.youtube.com/watch?v=lS9t6j-640Q",
      "published_at_utc": "2026-04-18T17:25:34+00:00",
      "age_seconds": 2893
    },
    {
      "channel": "perox",
      "title": "Почему?..😵 добьём 200к? тгк: Пекарня Пирога #baki #yujirohanma #боецбаки #perox #перокс",
      "url": "https://www.youtube.com/shorts/k8u69S_J9O4",
      "published_at_utc": "2026-04-18T16:48:58+00:00",
      "age_seconds": 4990
    },
    {
      "channel": "Собиратель новостей",
      "title": "Макрон Чуть НЕ ЗАСОСАЛ Мелони",
      "url": "https://www.youtube.com/shorts/MhVq8u2XEBg",
      "published_at_utc": "2026-04-18T16:27:11+00:00",
      "age_seconds": 6317
    },
    {
      "channel": "Vert Dider",
      "title": "Уже завтра, в воскресенье, встречаемся на нашем YouTube-канале.",
      "url": "https://www.youtube.com/shorts/yR52PJp-JLU",
      "published_at_utc": "2026-04-18T16:20:54+00:00",
      "age_seconds": 6667
    },
    {
      "channel": "sun_kill",
      "title": "мне не понравился камбек BTS",
      "url": "https://www.youtube.com/shorts/8ligBIT89aA",
      "published_at_utc": "2026-04-18T16:12:12+00:00",
      "age_seconds": 7197
    }
  ]
}