{
  "generated_at_utc": "2026-05-28T08:22:48.998530+00:00",
  "hours_window": 2,
  "items": [
    {
      "channel": "ПОСЛЕДНЯЯ ИЗВИЛИНА",
      "title": "Пасхалка от KFC",
      "url": "https://www.youtube.com/shorts/JX6AGvQf-HY",
      "published_at_utc": "2026-05-28T08:00:31+00:00",
      "age_seconds": 1259
    },
    {
      "channel": "Космос Просто",
      "title": "Как всего шесть чисел управляют Вселенной",
      "url": "https://www.youtube.com/watch?v=oo3SIhsJL5c",
      "published_at_utc": "2026-05-28T08:00:27+00:00",
      "age_seconds": 1241
    },
    {
      "channel": "FixEye - Роблокс",
      "title": "😱ИДЕАЛЬНЫЙ РАЗРЕЗ 50/50 В РОБЛОКС! МИРОВОЙ РЕКОРД!",
      "url": "https://www.youtube.com/watch?v=v1gk_OF8tPo",
      "published_at_utc": "2026-05-28T08:00:21+00:00",
      "age_seconds": 1310
    },
    {
      "channel": "ПРЕМИЯ ДАРВИНА",
      "title": "Партия тараканов",
      "url": "https://www.youtube.com/shorts/v0lUuUJsvqE",
      "published_at_utc": "2026-05-28T08:00:15+00:00",
      "age_seconds": 1275
    },
    {
      "channel": "Смешновости",
      "title": "Смешновости 175 - для веселого дня! 😂 #истории #история #новости #новость #shorts",
      "url": "https://www.youtube.com/shorts/Hcic_PpMmNM",
      "published_at_utc": "2026-05-28T08:00:04+00:00",
      "age_seconds": 1310
    },
    {
      "channel": "Собиратель новостей",
      "title": "Собака Мама Кормит Детей, Собака Папа Смотрит Телик",
      "url": "https://www.youtube.com/shorts/MpUs21YVwdQ",
      "published_at_utc": "2026-05-28T07:15:32+00:00",
      "age_seconds": 3953
    },
    {
      "channel": "ПОСЛЕДНЯЯ ИЗВИЛИНА",
      "title": "Олимпиада на допинге",
      "url": "https://www.youtube.com/shorts/QGOvE8YiE8A",
      "published_at_utc": "2026-05-28T07:00:32+00:00",
      "age_seconds": 4858
    },
    {
      "channel": "ПРЕМИЯ ДАРВИНА",
      "title": "Яблочный заговор",
      "url": "https://www.youtube.com/shorts/CigUITvzOwA",
      "published_at_utc": "2026-05-28T07:00:03+00:00",
      "age_seconds": 4887
    },
    {
      "channel": "Короче, новости",
      "title": "Школьники Трут Лысину Директора на Удачу",
      "url": "https://www.youtube.com/shorts/sQuaAbmnUxc",
      "published_at_utc": "2026-05-28T06:38:06+00:00",
      "age_seconds": 6200
    },
    {
      "channel": "Короче, новости",
      "title": "Ограбление Пятёрочек: Картонный Ваня Дмитриенко",
      "url": "https://www.youtube.com/shorts/GixRro1e5Ag",
      "published_at_utc": "2026-05-28T06:27:10+00:00",
      "age_seconds": 6856
    }
  ]
}